{
  "openapi": "3.0.0",
  "info": {
    "title": "Library API",
    "version": "1.0.0",
    "description": "Hotel Booking API"
  },
  "servers": [
    {
      "url": "http://localhost:5000/api/v1"
    }
  ],
  "paths": {
    "/auth/register": {
      "post": {
        "summary": "Create a new user",
        "tags": ["User"],
        "requestBody": {
          "required": true,
          "content": {
            "application/json": {
              "schema": {
                "$ref": "#/components/schemas/User"
              }
            }
          }
        },
        "responses": {
          "201": {
            "description": "The user was successfully created",
            "content": {
              "application/json": {
                "schema": {
                  "$ref": "#/components/schemas/User"
                }
              }
            }
          },
          "500": {
            "description": "Some server error"
          }
        }
      }
    },
    "/auth/login": {
      "post": {
        "summary": "Log-in to the system",
        "tags": ["User"],
        "requestBody": {
          "required": true,
          "content": {
            "application/json": {
              "schema": {
                "type": "object",
                "properties": {
                  "email": {
                    "type": "string"
                  },
                  "password": {
                    "type": "string"
                  }
                }
              }
            }
          }
        },
        "responses": {
          "201": {
            "description": "Log-in Successfully"
          },
          "500": {
            "description": "Some server error"
          }
        }
      }
    },
    "/auth/me": {
      "get": {
        "security": [
          {
            "bearerAuth": []
          }
        ],
        "summary": "Return information about me",
        "tags": ["User"],
        "responses": {
          "200": {
            "description": "My user profile",
            "content": {
              "application/json": {
                "schema": {
                  "$ref": "#/components/schemas/User"
                }
              }
            }
          },
          "500": {
            "description": "Some server error"
          }
        }
      }
    },
    "/bookings": {
      "get": {
        "security": [
          {
            "bearerAuth": []
          }
        ],
        "summary": "Returns the list of all the bookings",
        "tags": ["Bookings"],
        "parameters": [
          {
            "in": "query",
            "name": "hotelId",
            "schema": {
              "type": "string"
            },
            "required": false,
            "description": "The hotel id (Optional)"
          }
        ],
        "responses": {
          "200": {
            "description": "The list of the bookings",
            "content": {
              "application/json": {
                "schema": {
                  "type": "array",
                  "items": {
                    "$ref": "#/components/schemas/Booking"
                  }
                }
              }
            }
          }
        }
      }
    },
    "/hotels/{hotelId}/bookings": {
      "post": {
        "security": [
          {
            "bearerAuth": []
          }
        ],
        "summary": "Create a new Booking for the hotel specified by hotel id",
        "tags": ["Bookings"],
        "parameters": [
          {
            "in": "path",
            "name": "hotelId",
            "schema": {
              "type": "string"
            },
            "required": true,
            "description": "The hotel id"
          }
        ],
        "requestBody": {
          "required": true,
          "content": {
            "application/json": {
              "schema": {
                "$ref": "#/components/schemas/BookingBody"
              }
            }
          }
        },
        "responses": {
          "201": {
            "description": "The booking was successfully created",
            "content": {
              "application/json": {
                "schema": {
                  "$ref": "#/components/schemas/Booking"
                }
              }
            }
          },
          "500": {
            "description": "Some server error"
          }
        }
      }
    },
    "/bookings/{id}": {
      "get": {
        "security": [
          {
            "bearerAuth": []
          }
        ],
        "summary": "Get the booking by id",
        "tags": ["Bookings"],
        "parameters": [
          {
            "in": "path",
            "name": "id",
            "schema": {
              "type": "string"
            },
            "required": true,
            "description": "The booking id"
          }
        ],
        "responses": {
          "200": {
            "description": "The booking information by booking id",
            "content": {
              "application/json": {
                "schema": {
                  "$ref": "#/components/schemas/Booking"
                }
              }
            }
          },
          "404": {
            "description": "The booking was not found"
          }
        }
      },
      "put": {
        "security": [
          {
            "bearerAuth": []
          }
        ],
        "summary": "Update the booking by id",
        "tags": ["Bookings"],
        "parameters": [
          {
            "in": "path",
            "name": "id",
            "schema": {
              "type": "string"
            },
            "required": true,
            "description": "The booking id"
          }
        ],
        "requestBody": {
          "required": true,
          "content": {
            "application/json": {
              "schema": {
                "$ref": "#/components/schemas/BookingBody"
              }
            }
          }
        },
        "responses": {
          "200": {
            "description": "The booking was successfully updated",
            "content": {
              "application/json": {
                "schema": {
                  "$ref": "#/components/schemas/Booking"
                }
              }
            }
          },
          "404": {
            "description": "The booking was not found"
          }
        }
      },
      "delete": {
        "security": [
          {
            "bearerAuth": []
          }
        ],
        "summary": "Delete the booking by id",
        "tags": ["Bookings"],
        "parameters": [
          {
            "in": "path",
            "name": "id",
            "schema": {
              "type": "string"
            },
            "required": true,
            "description": "The booking id"
          }
        ],
        "responses": {
          "200": {
            "description": "The booking was successfully deleted",
            "content": {
              "application/json": {
                "schema": {
                  "$ref": "#/components/schemas/Booking"
                }
              }
            }
          },
          "404": {
            "description": "The booking was not found"
          }
        }
      }
    },
    "/hotels": {
      "post": {
        "security": [
          {
            "bearerAuth": []
          }
        ],
        "summary": "Create a new hotel",
        "tags": ["Hotels"],
        "requestBody": {
          "required": true,
          "content": {
            "application/json": {
              "schema": {
                "$ref": "#/components/schemas/Hotel"
              }
            }
          }
        },
        "responses": {
          "201": {
            "description": "The hotel was successfully created",
            "content": {
              "application/json": {
                "schema": {
                  "$ref": "#/components/schemas/Hotel"
                }
              }
            }
          },
          "500": {
            "description": "Some server error"
          }
        }
      },
      "get": {
        "summary": "Returns the list of all the hotels",
        "tags": ["Hotels"],
        "responses": {
          "200": {
            "description": "The list of the hotels",
            "content": {
              "application/json": {
                "schema": {
                  "type": "array",
                  "items": {
                    "$ref": "#/components/schemas/Hotel"
                  }
                }
              }
            }
          }
        }
      }
    },
    "/hotels/{id}": {
      "get": {
        "summary": "Get the hotel by id",
        "tags": ["Hotels"],
        "parameters": [
          {
            "in": "path",
            "name": "id",
            "schema": {
              "type": "string"
            },
            "required": true,
            "description": "The hotel id"
          }
        ],
        "responses": {
          "200": {
            "description": "The hotel description by id",
            "content": {
              "application/json": {
                "schema": {
                  "$ref": "#/components/schemas/Hotel"
                }
              }
            }
          },
          "404": {
            "description": "The hotel was not found"
          }
        }
      },
      "put": {
        "security": [
          {
            "bearerAuth": []
          }
        ],
        "summary": "Update the hotel by id",
        "tags": ["Hotels"],
        "parameters": [
          {
            "in": "path",
            "name": "id",
            "schema": {
              "type": "string"
            },
            "required": true,
            "description": "The hotel id"
          }
        ],
        "requestBody": {
          "required": true,
          "content": {
            "application/json": {
              "schema": {
                "$ref": "#/components/schemas/Hotel"
              }
            }
          }
        },
        "responses": {
          "200": {
            "description": "The hotel was successfully updated",
            "content": {
              "application/json": {
                "schema": {
                  "$ref": "#/components/schemas/Hotel"
                }
              }
            }
          },
          "500": {
            "description": "Some server error"
          }
        }
      },
      "delete": {
        "security": [
          {
            "bearerAuth": []
          }
        ],
        "summary": "Delete the hotel by id",
        "tags": ["Hotels"],
        "parameters": [
          {
            "in": "path",
            "name": "id",
            "schema": {
              "type": "string"
            },
            "required": true,
            "description": "The hotel id"
          }
        ],
        "responses": {
          "200": {
            "description": "The hotel was successfully deleted",
            "content": {
              "application/json": {
                "schema": {
                  "$ref": "#/components/schemas/Hotel"
                }
              }
            }
          },
          "404": {
            "description": "The hotel was not found"
          }
        }
      }
    }
  },
  "components": {
    "schemas": {
      "User": {
        "type": "object",
        "required": ["name", "email", "tel", "password"],
        "properties": {
          "name": {
            "type": "string",
            "description": "Name of user"
          },
          "email": {
            "type": "string",
            "description": "Email of user"
          },
          "tel": {
            "type": "string",
            "description": "Telephone number of user"
          },
          "role": {
            "type": "string",
            "description": "Role of user (admin or user), default is user"
          },
          "password": {
            "type": "string",
            "description": "Password of user"
          },
          "createdAt": {
            "type": "string",
            "format": "date",
            "example": "2023-08-20",
            "description": "Date of creation (default is current date-time)"
          }
        }
      },
      "Booking": {
        "type": "object",
        "required": ["bookingDate", "checkoutDate", "user", "hotel"],
        "properties": {
          "bookingDate": {
            "type": "string",
            "format": "date",
            "example": "2023-08-20",
            "description": "Check-In Date"
          },
          "checkoutDate": {
            "type": "string",
            "format": "date",
            "example": "2023-08-20",
            "description": "Check-In Date"
          },
          "user": {
            "type": "string",
            "description": "ID of the user making reservation"
          },
          "hotel": {
            "type": "string",
            "description": "ID of the hotel being reserved"
          },
          "createdAt": {
            "type": "string",
            "format": "date",
            "example": "2023-08-20",
            "description": "Date of creation (default is current date-time)"
          }
        }
      },
      "Hotel": {
        "type": "object",
        "required": [
          "name",
          "address",
          "district",
          "province",
          "postalcode",
          "picture"
        ],
        "properties": {
          "name": {
            "type": "string",
            "description": "Name of the hotel"
          },
          "address": {
            "type": "string",
            "description": "House No., Street, Road"
          },
          "district": {
            "type": "string",
            "description": "District"
          },
          "province": {
            "type": "string",
            "description": "province"
          },
          "postalcode": {
            "type": "string",
            "description": "5-digit postal code"
          },
          "tel": {
            "type": "string",
            "description": "telephone number"
          },
          "picture": {
            "type": "string",
            "description": "picture"
          }
        }
      },
      "BookingBody": {
        "type": "object",
        "required": ["bookingDate", "checkoutDate"],
        "properties": {
          "bookingDate": {
            "type": "string",
            "format": "date",
            "example": "2023-08-20",
            "description": "Check-In Date"
          },
          "checkoutDate": {
            "type": "string",
            "format": "date",
            "example": "2023-08-20",
            "description": "Check-In Date"
          },
          "createdAt": {
            "type": "string",
            "format": "date",
            "example": "2023-08-20",
            "description": "Date of creation (default is current date-time)"
          }
        }
      }
    },
    "securitySchemes": {
      "bearerAuth": {
        "type": "http",
        "scheme": "bearer",
        "bearerFormat": "JWT"
      }
    }
  },
  "tags": [
    {
      "name": "User",
      "description": "The user API"
    },
    {
      "name": "Bookings",
      "description": "The booking managing API"
    },
    {
      "name": "Hotels",
      "description": "The hotels managing API"
    }
  ]
}
